Metadata-Version: 2.1
Name: youtube-archivist
Version: 0.0.3
Summary: youtube indexer - keep track of your favorite channels!
Home-page: https://github.com/OpenJarbas/youtube_archivist
Author: jarbasai
Author-email: jarbasai@mailfence.com
License: apache2
Platform: UNKNOWN
